examples/__init__.py
openabm/__init__.py
openabm/oabm_tools.py
openabm/examples/__init__.py
openabm/examples/bank_reserves/__init__.py
openabm/examples/bank_reserves/batch_run.py
openabm/examples/bank_reserves/run.py
openabm/examples/bank_reserves/bank_reserves/__init__.py
openabm/examples/bank_reserves/bank_reserves/agents.py
openabm/examples/bank_reserves/bank_reserves/model.py
openabm/examples/bank_reserves/bank_reserves/random_walk.py
openabm/examples/bank_reserves/bank_reserves/server.py
openabm/examples/boid_flockers/__init__.py
openabm/examples/boid_flockers/run.py
openabm/examples/boid_flockers/boid_flockers/SimpleContinuousModule.py
openabm/examples/boid_flockers/boid_flockers/__init__.py
openabm/examples/boid_flockers/boid_flockers/boid.py
openabm/examples/boid_flockers/boid_flockers/model.py
openabm/examples/boid_flockers/boid_flockers/server.py
openabm/examples/boltzmann_wealth_model/__init__.py
openabm/examples/boltzmann_wealth_model/run.py
openabm/examples/boltzmann_wealth_model/boltzmann_wealth_model/__init__.py
openabm/examples/boltzmann_wealth_model/boltzmann_wealth_model/model.py
openabm/examples/boltzmann_wealth_model/boltzmann_wealth_model/server.py
openabm/examples/boltzmann_wealth_model_network/__init__.py
openabm/examples/boltzmann_wealth_model_network/run.py
openabm/examples/boltzmann_wealth_model_network/boltzmann_wealth_model_network/__init__.py
openabm/examples/boltzmann_wealth_model_network/boltzmann_wealth_model_network/model.py
openabm/examples/boltzmann_wealth_model_network/boltzmann_wealth_model_network/server.py
openabm/examples/charts/__init__.py
openabm/examples/charts/run.py
openabm/examples/charts/charts/__init__.py
openabm/examples/charts/charts/agents.py
openabm/examples/charts/charts/model.py
openabm/examples/charts/charts/random_walk.py
openabm/examples/charts/charts/server.py
openabm/examples/conways_game_of_life/__init__.py
openabm/examples/conways_game_of_life/run.py
openabm-1.0.12.dist-info/METADATA
openabm-1.0.12.dist-info/WHEEL
openabm-1.0.12.dist-info/entry_points.txt
openabm-1.0.12.dist-info/top_level.txt
openabm-1.0.12.dist-info/RECORD
