Metadata-Version: 2.1
Name: openabm
Version: 1.0.12
Summary: A Python framework for agent-based modeling based on MESA
Home-page: https://github.com/cma43/Open-ABM
Author: Conor M. Artman
Author-email: cmartman@ncsu.edu
License: MIT
Platform: UNKNOWN
Classifier: License :: OSI Approved :: MIT License
Classifier: Programming Language :: Python :: 3
Classifier: Programming Language :: Python :: 3.7
Requires-Dist: mesa
